unityapiclient/__init__.py
unityapiclient/client.py
unityapiclient-0.0.3.dist-info/DESCRIPTION.rst
unityapiclient-0.0.3.dist-info/METADATA
unityapiclient-0.0.3.dist-info/RECORD
unityapiclient-0.0.3.dist-info/WHEEL
unityapiclient-0.0.3.dist-info/metadata.json
unityapiclient-0.0.3.dist-info/top_level.txt
