Metadata-Version: 2.0
Name: unityapiclient
Version: 0.0.3
Summary: Client library for the Unity IDM APIs
Home-page: http://eudat-b2access.github.io/unity-api-python-client
Author: Nicolas Liampotis
Author-email: nliam@grnet.gr
License: Apache License 2.0
Download-URL: https://github.com/EUDAT-B2ACCESS/unity-api-python-client
Keywords: unity identity management rest api client library
Platform: UNKNOWN
Classifier: Development Status :: 3 - Alpha
Classifier: Programming Language :: Python :: 2
Classifier: Programming Language :: Python :: 2.6
Classifier: Programming Language :: Python :: 2.7
Classifier: License :: OSI Approved :: Apache Software License
Classifier: Intended Audience :: Developers
Classifier: Topic :: Software Development :: Libraries :: Python Modules
Requires-Python: >=2.6,<2.8
Requires-Dist: requests
Requires-Dist: pytz
Provides-Extra: security
Requires-Dist: pyOpenSSL (>=0.14); extra == 'security'
Requires-Dist: cryptography (>=1.3.4); extra == 'security'
Requires-Dist: idna (>=2.0.0); extra == 'security'
